{
  "annotations": {
    "changelogDate": "20240610120607"
  },
  "applications": "*",
  "dto": "mapstruct",
  "fields": [
    {
      "fieldName": "id",
      "fieldType": "UUID",
      "options": {
        "id": true
      }
    },
    {
      "fieldName": "type",
      "fieldType": "PaymentParamType",
      "fieldValues": "USER_INPUT,FETCH_RESPONSE,NONE"
    },
    {
      "fieldName": "name",
      "fieldType": "String"
    },
    {
      "fieldName": "value",
      "fieldType": "String"
    },
    {
      "fieldName": "dataType",
      "fieldType": "DataType",
      "fieldValidateRules": ["required"],
      "fieldValues": "COLLECTION,STRING,INT,DOUBLE,BOOLEAN,DATETIME,NONE"
    }
  ],
  "name": "PaymentParam",
  "relationships": [],
  "searchEngine": "no",
  "service": "serviceImpl"
}
